pingVisualizer/__init__.py
pingVisualizer/pingVisualizer.py
pingVisualizer-0.1.0.dist-info/DESCRIPTION.rst
pingVisualizer-0.1.0.dist-info/METADATA
pingVisualizer-0.1.0.dist-info/top_level.txt
pingVisualizer-0.1.0.dist-info/RECORD
pingVisualizer-0.1.0.dist-info/WHEEL
pingVisualizer-0.1.0.dist-info/metadata.json
