Metadata-Version: 2.0
Name: pingVisualizer
Version: 0.1.0
Summary: Visualizes ping responses in braillcurves
Home-page: https://github.com/gurkslask/pingVisualizer
Author: Alexander Svensson
Author-email: gurkslask@gmail.com
License: BSD
Keywords: pingVisualizer
Platform: UNKNOWN
Classifier: Development Status :: 2 - Pre-Alpha
Classifier: Intended Audience :: Developers
Classifier: License :: OSI Approved :: BSD License
Classifier: Natural Language :: Swedish
Classifier: Programming Language :: Python :: 3
Classifier: Programming Language :: Python :: 3.3
Classifier: Programming Language :: Python :: 3.4
Requires-Dist: braillegraph
